solidity_python_sdk/__init__.py
solidity_python_sdk/main.py
solidity_python_sdk/contracts/__init__.py
solidity_python_sdk/contracts/batch.py
solidity_python_sdk/contracts/geolocation.py
solidity_python_sdk/contracts/product_passport.py
solidity_python_sdk/resources/__init__.py
solidity_python_sdk/resources/ABI/__init__.py
solidity_python_sdk/resources/ABI/Batch.sol/Batch.dbg.json
solidity_python_sdk/resources/ABI/Batch.sol/Batch.json
solidity_python_sdk/resources/ABI/ComplexManagement.sol/ComplexManagement.dbg.json
solidity_python_sdk/resources/ABI/ComplexManagement.sol/ComplexManagement.json
solidity_python_sdk/resources/ABI/Geolocation.sol/Geolocation.dbg.json
solidity_python_sdk/resources/ABI/Geolocation.sol/Geolocation.json
solidity_python_sdk/resources/ABI/ProductDetails.sol/ProductDetails.dbg.json
solidity_python_sdk/resources/ABI/ProductDetails.sol/ProductDetails.json
solidity_python_sdk/resources/ABI/ProductPassport.sol/ProductPassport.dbg.json
solidity_python_sdk/resources/ABI/ProductPassport.sol/ProductPassport.json
solidity_python_sdk/utils/__init__.py
solidity_python_sdk/utils/error_handling.py
solidity_python_sdk/utils/pinata_utils.py
solidity_python_sdk/utils/utils.py
solidity_python_sdk-0.1.26.dist-info/METADATA
solidity_python_sdk-0.1.26.dist-info/WHEEL
solidity_python_sdk-0.1.26.dist-info/top_level.txt
solidity_python_sdk-0.1.26.dist-info/RECORD
