Metadata-Version: 2.1
Name: solidity-python-sdk
Version: 0.1.26
Summary: SDK for interacting with Digital Product Passport smart contracts
Author-email: Luthiano Trarbach <bhagah.trarbach@gmail.com>
License: MIT
Project-URL: Homepage, https://github.com/DigitalProductPassport/solidity-python-sdk
Requires-Python: >=3.6
Requires-Dist: web3
Requires-Dist: python-dotenv
Requires-Dist: requests
Requires-Dist: pinatapy-vourhey
Requires-Dist: eth-tester
